dotools_py/__init__.py
dotools_py/logger.py
dotools_py/utils.py
dotools_py/_experimental/__init__.py
dotools_py/_experimental/_deprecated/_ReadWrite_RDS.R
dotools_py/_experimental/_deprecated/_run_MAST.R
dotools_py/_experimental/gr/__init__.py
dotools_py/_experimental/gr/_generic.py
dotools_py/dt/__init__.py
dotools_py/dt/_datasets.py
dotools_py/dt/_markers.py
dotools_py/dt/example_reduced.h5ad
dotools_py/get/__init__.py
dotools_py/get/_generic.py
dotools_py/pl/_Plotter.py
dotools_py/pl/_StatsPlotter.py
dotools_py/pl/__init__.py
dotools_py/pl/_dotplot.py
dotools_py/pl/_downstream.py
dotools_py/pl/_embeddings.py
dotools_py/pl/_experimental.py
dotools_py/pl/_expression.py
dotools_py/pl/_heatmap.py
dotools_py/pl/_visium.py
dotools_py/pp/__init__.py
dotools_py/pp/_cellbender.py
dotools_py/pp/_importer.py
dotools_py/settings/__init__.py
dotools_py/settings/_configure.py
dotools_py/settings/_global_parameters.py
dotools_py/tl/__init__.py
dotools_py/tl/_analysis.py
dotools_py/tl/_get_stats.py
dotools_py/tl/_rankGenes.py
dotools_py/tl/_statistics.py
dotools_py/util_scripts/_run_CCA.R
dotools_py/util_scripts/_run_CellBender.sh
dotools_py/util_scripts/_run_SCTransform.R
dotools_py/util_scripts/_run_edgeR.R
dotools_py/util_scripts/_run_scDblFinder.R
dotools_py/utility/HomoSapiens_GeneMetadata.pickle.gz
dotools_py/utility/MusMusculus_GeneMetadata.pickle.gz
dotools_py/utility/__init__.py
dotools_py/utility/_general.py
dotools_py/utility/_language.py
dotools_py/utility/_plotting.py
dotools_py/utility/_spatial.py
dotools_py-1.0.0.dist-info/METADATA
dotools_py-1.0.0.dist-info/WHEEL
dotools_py-1.0.0.dist-info/licenses/LICENSE
dotools_py-1.0.0.dist-info/RECORD
