Metadata-Version: 2.4
Name: DOTools_py
Version: 1.0.0
Summary: Convenient functions to streamline sc/snRNAseq data analysis workflow
Project-URL: Documentation, https://DOTools_py.readthedocs.io/
Project-URL: Homepage, https://github.com/davidrm-bio/DOTools_py
Project-URL: Source, https://github.com/davidrm-bio/DOTools_py
Author: David Rodriguez Morales, Mariano Ruz Jurado, David John
Maintainer-email: David Rodriguez Morales <rodriguezmorales@med.uni-frankfurt.de>
License: MIT License
License-File: LICENSE
Classifier: Programming Language :: Python :: 3 :: Only
Classifier: Programming Language :: Python :: 3.10
Classifier: Programming Language :: Python :: 3.11
Classifier: Programming Language :: Python :: 3.12
Classifier: Programming Language :: Python :: 3.13
Requires-Python: >=3.10
Requires-Dist: adjusttext
Requires-Dist: anndata>=0.9.2
Requires-Dist: bbknn
Requires-Dist: celltypist
Requires-Dist: doubletdetection>=4.3
Requires-Dist: fast-array-utils[accel,sparse]>=1.2.1; python_version >= '3.11'
Requires-Dist: gseapy
Requires-Dist: harmonypy
Requires-Dist: jupyter
Requires-Dist: numba
Requires-Dist: numpy>=1.26.4
Requires-Dist: pandas>=2.2.3
Requires-Dist: polars>=1.30
Requires-Dist: pydeseq2
Requires-Dist: requests
Requires-Dist: scanorama
Requires-Dist: scanpro
Requires-Dist: scanpy
Requires-Dist: scikit-image
Requires-Dist: scipy
Requires-Dist: scvi-tools>=1.3
Requires-Dist: session-info2
Requires-Dist: tqdm
Provides-Extra: dev
Requires-Dist: pre-commit; extra == 'dev'
Requires-Dist: twine>=4.0.2; extra == 'dev'
Provides-Extra: doc
Requires-Dist: bbknn; extra == 'doc'
Requires-Dist: celltypist; extra == 'doc'
Requires-Dist: docutils!=0.18.*,!=0.19.*,>=0.8; extra == 'doc'
Requires-Dist: doubletdetection; extra == 'doc'
Requires-Dist: gseapy; extra == 'doc'
Requires-Dist: ipykernel; extra == 'doc'
Requires-Dist: ipython; extra == 'doc'
Requires-Dist: jupyter; extra == 'doc'
Requires-Dist: matplotlib; extra == 'doc'
Requires-Dist: myst-nb>=1.1; extra == 'doc'
Requires-Dist: pandas; extra == 'doc'
Requires-Dist: polars; extra == 'doc'
Requires-Dist: pydeseq2; extra == 'doc'
Requires-Dist: scanpydoc; extra == 'doc'
Requires-Dist: scipy; extra == 'doc'
Requires-Dist: scvi-tools; extra == 'doc'
Requires-Dist: seaborn; extra == 'doc'
Requires-Dist: setuptools; extra == 'doc'
Requires-Dist: sphinx-autodoc-typehints; extra == 'doc'
Requires-Dist: sphinx-book-theme>=1; extra == 'doc'
Requires-Dist: sphinx-copybutton; extra == 'doc'
Requires-Dist: sphinx-design; extra == 'doc'
Requires-Dist: sphinx-tabs; extra == 'doc'
Requires-Dist: sphinx>=8.1; extra == 'doc'
Requires-Dist: sphinxcontrib-bibtex>=1; extra == 'doc'
Requires-Dist: sphinxext-opengraph; extra == 'doc'
Requires-Dist: tqdm; extra == 'doc'
Provides-Extra: test
Requires-Dist: adjusttext; extra == 'test'
Requires-Dist: anndata; extra == 'test'
Requires-Dist: bbknn; extra == 'test'
Requires-Dist: celltypist; extra == 'test'
Requires-Dist: coverage; extra == 'test'
Requires-Dist: doubletdetection; extra == 'test'
Requires-Dist: gseapy; extra == 'test'
Requires-Dist: ipython; extra == 'test'
Requires-Dist: matplotlib; extra == 'test'
Requires-Dist: numba; extra == 'test'
Requires-Dist: numpy; extra == 'test'
Requires-Dist: pandas; extra == 'test'
Requires-Dist: polars; extra == 'test'
Requires-Dist: pyarrow; extra == 'test'
Requires-Dist: pytest; extra == 'test'
Requires-Dist: scanpy; extra == 'test'
Requires-Dist: scipy; extra == 'test'
Requires-Dist: scvi-tools; extra == 'test'
Requires-Dist: seaborn; extra == 'test'
Requires-Dist: tqdm; extra == 'test'
